<annotation verified="yes">
	<folder>images</folder>
	<filename>33.jpg</filename>
	<path>C:\Users\86150\Desktop\Mushroom\train\images\33.jpg</path>
	<source>
		<database>Unknown</database>
	</source>
	<size>
		<width>610</width>
		<height>610</height>
		<depth>3</depth>
	</size>
	<segmented>0</segmented>
	<object>
		<name>H</name>
		<pose>Unspecified</pose>
		<truncated>0</truncated>
		<difficult>0</difficult>
		<bndbox>
			<xmin>160</xmin>
			<ymin>42</ymin>
			<xmax>421</xmax>
			<ymax>217</ymax>
		</bndbox>
	</object>
	<object>
		<name>H</name>
		<pose>Unspecified</pose>
		<truncated>0</truncated>
		<difficult>0</difficult>
		<bndbox>
			<xmin>48</xmin>
			<ymin>181</ymin>
			<xmax>217</xmax>
			<ymax>442</ymax>
		</bndbox>
	</object>
	<object>
		<name>H</name>
		<pose>Unspecified</pose>
		<truncated>0</truncated>
		<difficult>0</difficult>
		<bndbox>
			<xmin>240</xmin>
			<ymin>231</ymin>
			<xmax>425</xmax>
			<ymax>466</ymax>
		</bndbox>
	</object>
	<object>
		<name>H</name>
		<pose>Unspecified</pose>
		<truncated>0</truncated>
		<difficult>0</difficult>
		<bndbox>
			<xmin>377</xmin>
			<ymin>58</ymin>
			<xmax>526</xmax>
			<ymax>176</ymax>
		</bndbox>
	</object>
</annotation>
